beetsplug/__init__.py
beetsplug/alias.py
beets_alias-1.0.1.dist-info/LICENSE
beets_alias-1.0.1.dist-info/METADATA
beets_alias-1.0.1.dist-info/WHEEL
beets_alias-1.0.1.dist-info/RECORD
