Metadata-Version: 2.1
Name: beets-alias
Version: 1.0.1
Summary: Alias Plugin for Beets
Home-page: https://github.com/kergoth/beets-alias
License: MIT
Author: Christopher Larson
Author-email: kergoth@gmail.com
Requires-Python: >=3.8,<3.11
Classifier: Development Status :: 4 - Beta
Classifier: Environment :: Plugins
Classifier: License :: OSI Approved :: MIT License
Classifier: Programming Language :: Python
Classifier: Programming Language :: Python :: 3
Classifier: Programming Language :: Python :: 3.8
Classifier: Programming Language :: Python :: 3.9
Classifier: Programming Language :: Python :: 3.10
Classifier: Topic :: Multimedia :: Sound/Audio
Requires-Dist: beets (>=2.0.0,<3.0.0)
Project-URL: Changelog, https://github.com/kergoth/beets-alias/releases
Project-URL: Documentation, https://beets-alias.readthedocs.io
Project-URL: Repository, https://github.com/kergoth/beets-alias
